sglite.pyd
xcore/__init__.py
xcore/app.py
xcore/diffraction.py
xcore/formats.py
xcore/generate_py_files.py
xcore/laue_symops.py
xcore/multiplicity.py
xcore/permutations.py
xcore/sglite.pyd
xcore/spacegroup.py
xcore/spacegroups.txt
xcore/unitcell.py
xcore/version.py
xcore/wyckoff.py
xcore/scattering/__init__.py
xcore/scattering/atomic_radii.py
xcore/scattering/dt1968.py
xcore/scattering/it_table_4322.py
xcore/scattering/it_table_4323.py
xcore/scattering/peng1998.py
xcore/scattering/wk1995.py
xcore-0.7.2.data/headers/sgconst.h
xcore-0.7.2.data/headers/sglite.h
xcore-0.7.2.data/headers/sgrefset.h
xcore-0.7.2.dist-info/DESCRIPTION.rst
xcore-0.7.2.dist-info/METADATA
xcore-0.7.2.dist-info/RECORD
xcore-0.7.2.dist-info/WHEEL
xcore-0.7.2.dist-info/entry_points.txt
xcore-0.7.2.dist-info/metadata.json
xcore-0.7.2.dist-info/top_level.txt
