Metadata-Version: 2.0
Name: xcore
Version: 0.7.2
Summary: Crystallographic space group library in Python
Home-page: https://github.com/stefsmeets/xcore
Author: Stef Smeets
Author-email: stef.smeets@mmk.su.se
License: GPL
Platform: UNKNOWN
Classifier: Programming Language :: Python :: 2.7
Requires-Dist: numpy
Requires-Dist: pandas
